CHANGELOG.md
MANIFEST.in
README.md
setup.cfg
setup.py
versioneer.py
src/libreflow/__init__.py
src/libreflow.extensions.file_manager.synchronisation.egg-info/PKG-INFO
src/libreflow.extensions.file_manager.synchronisation.egg-info/SOURCES.txt
src/libreflow.extensions.file_manager.synchronisation.egg-info/dependency_links.txt
src/libreflow.extensions.file_manager.synchronisation.egg-info/top_level.txt
src/libreflow/extensions/__init__.py
src/libreflow/extensions/file_manager/__init__.py
src/libreflow/extensions/file_manager/synchronisation/__init__.py
src/libreflow/extensions/file_manager/synchronisation/_version.py
src/libreflow/extensions/file_manager/synchronisation/error.py
src/libreflow/extensions/file_manager/synchronisation/file.py
src/libreflow/extensions/file_manager/synchronisation/request_rules.py
src/libreflow/extensions/file_manager/synchronisation/request_session.py
src/libreflow/extensions/file_manager/synchronisation/shot.py
src/libreflow/extensions/file_manager/synchronisation/sync_utils.py