Metadata-Version: 2.4
Name: libreflow.extensions.file-manager.synchronisation
Version: 1.2.0
Summary: Libreflow extension to batch manage sync and requests
Home-page: https://gitlab.com/lfs.coop/libreflow/extensions/file_manager/synchronisation
Author: LFS
Author-email: libreflow@lfs.coop
License: LGPLv3+
Keywords: kabaret libreflow
Classifier: Programming Language :: Python :: 3
Classifier: Intended Audience :: Developers
Classifier: License :: OSI Approved :: GNU Lesser General Public License v3 or later (LGPLv3+)
Classifier: Operating System :: OS Independent
Requires-Python: >=3.7
Dynamic: author
Dynamic: author-email
Dynamic: classifier
Dynamic: description
Dynamic: description-content-type
Dynamic: home-page
Dynamic: keywords
Dynamic: license
Dynamic: requires-python
Dynamic: summary
